torchmanager/__init__.py
torchmanager/basic.py
torchmanager/callbacks/__init__.py
torchmanager/callbacks/callback.py
torchmanager/callbacks/ckpt.py
torchmanager/callbacks/dynamic.py
torchmanager/callbacks/early_stop.py
torchmanager/callbacks/experiment.py
torchmanager/callbacks/functional.py
torchmanager/callbacks/lr.py
torchmanager/callbacks/progress.py
torchmanager/callbacks/tensorboard.py
torchmanager/configs/__init__.py
torchmanager/configs/basic.py
torchmanager/configs/json.py
torchmanager/configs/yaml.py
torchmanager/data/__init__.py
torchmanager/data/dataset.py
torchmanager/data/sliding.py
torchmanager/losses/__init__.py
torchmanager/losses/cross_entropy.py
torchmanager/losses/dice.py
torchmanager/losses/loss.py
torchmanager/losses/mse.py
torchmanager/losses/protocols.py
torchmanager/metrics/__init__.py
torchmanager/metrics/accuracy.py
torchmanager/metrics/conf_mat.py
torchmanager/metrics/extractor.py
torchmanager/metrics/iou.py
torchmanager/metrics/metric.py
torchmanager/metrics/similarity.py
torchmanager/testing.py
torchmanager/training.py
torchmanager_core/__init__.py
torchmanager_core/backward/__init__.py
torchmanager_core/backward/hook.py
torchmanager_core/backward/protocols.py
torchmanager_core/checkpoint/__init__.py
torchmanager_core/checkpoint/ckpt.py
torchmanager_core/checkpoint/protocols.py
torchmanager_core/devices/__init__.py
torchmanager_core/devices/device.py
torchmanager_core/devices/protocols.py
torchmanager_core/errors/__init__.py
torchmanager_core/errors/configs.py
torchmanager_core/errors/runtime.py
torchmanager_core/errors/train.py
torchmanager_core/errors/version.py
torchmanager_core/protocols.py
torchmanager_core/random/__init__.py
torchmanager_core/random/random.py
torchmanager_core/random/seed.py
torchmanager_core/typing.py
torchmanager_core/version/__init__.py
torchmanager_core/version/deprecation.py
torchmanager_core/version/details.py
torchmanager_core/version/errors.py
torchmanager_core/version/version.py
torchmanager-1.4.3.dist-info/METADATA
torchmanager-1.4.3.dist-info/WHEEL
torchmanager-1.4.3.dist-info/licenses/LICENSE
torchmanager-1.4.3.dist-info/RECORD
