Metadata-Version: 2.4
Name: torchmanager
Version: 1.4.3
Summary: PyTorch Training Manager v1.4.3
License-File: LICENSE
Author: Qisheng He
Author-email: Qisheng.He@wayne.edu
Requires-Python: >=3.10,<4.0
Classifier: Programming Language :: Python :: 3
Classifier: Programming Language :: Python :: 3.10
Classifier: Programming Language :: Python :: 3.11
Classifier: Programming Language :: Python :: 3.12
Classifier: Programming Language :: Python :: 3.13
Classifier: Programming Language :: Python :: 3.14
Provides-Extra: all
Provides-Extra: scipy
Provides-Extra: tensorboard
Provides-Extra: yaml
Requires-Dist: packaging (>=16.8)
Requires-Dist: torch
Requires-Dist: tqdm
Project-URL: Repository, https://github.com/kisonho/torchmanager.git
